{"a": {"name": "a", "quant": "1", "unit": "a", "sel": false, "place": "Fridge"}, "b": {"name": "b", "quant": "1", "unit": "b", "sel": false, "place": "Fridge"}, "c": {"name": "c", "quant": "1", "unit": "c", "sel": false, "place": "Fridge"}, "d": {"name": "d", "quant": "1", "unit": "d", "sel": false, "place": "Fridge"}, "e": {"name": "e", "quant": "1", "unit": "e", "sel": false, "place": "Fridge"}, "f": {"name": "f", "quant": "1", "unit": "f", "sel": false, "place": "Fridge"}, "g": {"name": "g", "quant": "1", "unit": "g", "sel": false, "place": "Fridge"}, "i": {"name": "i", "quant": "1", "unit": "i", "sel": false, "place": "Fridge"}, "j": {"name": "j", "quant": "4.2934", "unit": "j", "sel": false, "place": "Fridge"}, "aa": {"name": "aa", "quant": "1", "unit": "a", "sel": false, "place": "Freezer"}, "bb": {"name": "bb", "quant": "1", "unit": "b", "sel": false, "place": "Freezer"}, "cc": {"name": "cc", "quant": "1", "unit": "c", "sel": false, "place": "Freezer"}, "dd": {"name": "dd", "quant": "1", "unit": "d", "sel": false, "place": "Freezer"}, "ee": {"name": "ee", "quant": "1", "unit": "e", "sel": false, "place": "Freezer"}, "ff": {"name": "ff", "quant": "1", "unit": "f", "sel": false, "place": "Freezer"}, "gg": {"name": "gg", "quant": "1", "unit": "g", "sel": false, "place": "Freezer"}, "hh": {"name": "hh", "quant": "1", "unit": "h", "sel": false, "place": "Freezer"}, "ii": {"name": "ii", "quant": "1", "unit": "i", "sel": false, "place": "Freezer"}}